pytest_unflakable/__init__.py
pytest_unflakable/_api.py
pytest_unflakable/_git.py
pytest_unflakable/_plugin.py
pytest_unflakable-0.2.0.dist-info/LICENSE
pytest_unflakable-0.2.0.dist-info/METADATA
pytest_unflakable-0.2.0.dist-info/WHEEL
pytest_unflakable-0.2.0.dist-info/entry_points.txt
pytest_unflakable-0.2.0.dist-info/top_level.txt
pytest_unflakable-0.2.0.dist-info/RECORD
